darkcat/__init__.py
darkcat/cli.py
darkcat/version.py
darkcat/commands/__init__.py
darkcat/commands/add.py
darkcat/commands/doctor.py
darkcat/commands/init.py
darkcat/commands/wizard.py
darkcat/utils/__init__.py
darkcat-1.0.0.dist-info/licenses/LICENSE
darkcat-1.0.0.dist-info/METADATA
darkcat-1.0.0.dist-info/WHEEL
darkcat-1.0.0.dist-info/entry_points.txt
darkcat-1.0.0.dist-info/top_level.txt
darkcat-1.0.0.dist-info/RECORD
