Metadata-Version: 2.4
Name: darkcat
Version: 1.0.0
License-File: LICENSE
Requires-Dist: click
Requires-Dist: rich
Dynamic: license-file
Dynamic: requires-dist
